layered_persistence/__init__.py
layered_persistence/file_layer.py
layered_persistence/http_layer.py
layered_persistence/persistence.py
layered_persistence/runtime_layer.py
layered_persistence/serve_via_http.py
layered_persistence-0.0.2.dist-info/METADATA
layered_persistence-0.0.2.dist-info/WHEEL
layered_persistence-0.0.2.dist-info/licenses/LICENSE
layered_persistence-0.0.2.dist-info/RECORD
