Metadata-Version: 2.4
Name: layered-persistence
Version: 0.0.2
Summary: Persistence
Project-URL: Homepage, https://github.com/ceil-python/persistence
Author-email: Sergey Shkatula <sergey@ceil.dev>
License-Expression: MIT
License-File: LICENSE
Keywords: layers,persistence,storage
Requires-Python: >=3.7
